{
  "letters": [
    {
      "ch": "k",
      "tipCount": 11458,
      "tipW": 0.3085,
      "midW": 0.8266,
      "bulbRatio": 0.373,
      "hang": 1.2966
    },
    {
      "ch": "l",
      "tipCount": 4134,
      "tipW": 0.2661,
      "midW": 0.3458,
      "bulbRatio": 0.769,
      "hang": 1.2519
    },
    {
      "ch": "a",
      "tipCount": 8156,
      "tipW": 0.2997,
      "midW": 0.9421,
      "bulbRatio": 0.318,
      "hang": 1.1057
    },
    {
      "ch": "u",
      "tipCount": 6368,
      "tipW": 0.2717,
      "midW": 0.8858,
      "bulbRatio": 0.307,
      "hang": 1.0415
    },
    {
      "ch": "t",
      "tipCount": 7600,
      "tipW": 0.3104,
      "midW": 0.4198,
      "bulbRatio": 0.739,
      "hang": 1.3045
    },
    {
      "ch": ".",
      "tipCount": 62,
      "tipW": 0.2528,
      "midW": 0.316,
      "bulbRatio": 0.8,
      "hang": 0.5847
    },
    {
      "ch": "p",
      "tipCount": 5126,
      "tipW": 0.1306,
      "midW": 0.9096,
      "bulbRatio": 0.144,
      "hang": 1.3176
    },
    {
      "ch": "r",
      "tipCount": 2877,
      "tipW": 0.2368,
      "midW": 0.4935,
      "bulbRatio": 0.48,
      "hang": 1.0214
    },
    {
      "ch": "o",
      "tipCount": 5492,
      "tipW": 0.3727,
      "midW": 0.9723,
      "bulbRatio": 0.383,
      "hang": 1.0867
    }
  ],
  "meanBulbRatio": 0.479,
  "bulbsOver13": 0,
  "frozen": true,
  "params": {
    "gravity": 0.9,
    "viscosity": 0.9,
    "freezeHeight": 0.68
  },
  "bg": "rgb(12, 16, 24)",
  "tipWeld": {
    "welded": 0,
    "bridges": 0,
    "strandsKilled": 0,
    "lipSoftened": 0,
    "loftShared": 0,
    "loftVerts": 0,
    "tipCount": 86560,
    "bakedSoftLetters": 9,
    "tipWeldFlag": false,
    "tipLoftFlag": false,
    "sharedVertexFlag": false,
    "lipSoftFlag": false,
    "softBooleanBakeFlag": true
  }
}